[
  "Seleccionar Temporada",
  [],
  "Temporada 1",
  [
    {
      "cap": 1,
      "link": "https://watchsb.com/e/c83dcajlcjg6"
    },
    {
      "cap": 2,
      "link": "https://watchsb.com/e/n0cnxy47c2tu"
    },
    {
      "cap": 3,
      "link": "https://watchsb.com/e/h9c38ro788cm"
    },
    {
      "cap": 4,
      "link": "https://watchsb.com/e/r90mm6fqz7hx"
    },
    {
      "cap": 5,
      "link": "https://watchsb.com/e/lfkwujx3hoy3"
    },
    {
      "cap": 6,
      "link": "https://watchsb.com/e/ax9rwhbd1jfi"
    },
    {
      "cap": 7,
      "link": "https://watchsb.com/e/hx9dgkytjgvn"
    },
    {
      "cap": 8,
      "link": "https://watchsb.com/e/ogk1i8pp3xvd"
    }
  ],
  "Temporada 2",
  [
    {
      "cap": 1,
      "link": "https://watchsb.com/e/nfhai35zz73u"
    },
    {
      "cap": 2,
      "link": "https://watchsb.com/e/niss2g5dctdu"
    },
    {
      "cap": 3,
      "link": "https://watchsb.com/e/ovp3u04gege6"
    },
    {
      "cap": 4,
      "link": "https://watchsb.com/e/4t6nwvsl3axl"
    },
    {
      "cap": 5,
      "link": "https://watchsb.com/e/nl68jkywpbfy"
    },
    {
      "cap": 6,
      "link": "https://watchsb.com/e/qx0tcp8dtolp"
    },
    {
      "cap": 7,
      "link": "https://watchsb.com/e/rt2cicdrhbyu"
    },
    {
      "cap": 8,
      "link": "https://watchsb.com/e/ygadntjntnny"
    }
  ],
  "Temporada 3",
  [
    {
      "cap": 1,
      "link": "https://watchsb.com/e/0ln209mktt8r"
    },
    {
      "cap": 2,
      "link": "https://watchsb.com/e/svoi6itcb5j1"
    },
    {
      "cap": 3,
      "link": "https://watchsb.com/e/0e1euqe0fy5d"
    },
    {
      "cap": 4,
      "link": "https://watchsb.com/e/l54rcak6rf7g"
    },
    {
      "cap": 5,
      "link": "https://watchsb.com/e/5rtwczmujrmg"
    },
    {
      "cap": 6,
      "link": "https://watchsb.com/e/dfwubi4xu32i"
    },
    {
      "cap": 7,
      "link": "https://watchsb.com/e/ecr0zreaol0x"
    },
    {
      "cap": 8,
      "link": "https://watchsb.com/e/saer19wybsfz"
    }
  ],
  "Temporada 4",
  [
    {
      "cap": 1,
      "link": "https://okru.link/v2/embed_c8.html?t=VAiJvnsyeET_layFarr3fx4.IIquvH6yQd.S9wKk7.NSZw.29EQhiRu4_aqj2osL9h05sjb2HnLljR2pn0BCVFqK0yOqXmF4KiYZi.KeFKu5mfELBWPxuV3X1YGqmKD0"
    },
    {
      "cap": 2,
      "link": "https://okru.link/v2/embed_c8.html?t=VAiJvnsyeET_layFarr3fyH_ZQuhgE2LPB4.RIGHy0Cva2Py8uHT9F.8Zejkpq_OxbVX6kqRBmMWI90lwvshqLX4Z1HH0mQC5LWhIje4tkw_Y.sHybKzGSM5vTQYj8S3"
    }
  ]
]
